bower/__init__.py
bower/github.py
bower/main.py
bower.py-1.0.dist-info/DESCRIPTION.rst
bower.py-1.0.dist-info/entry_points.txt
bower.py-1.0.dist-info/METADATA
bower.py-1.0.dist-info/metadata.json
bower.py-1.0.dist-info/RECORD
bower.py-1.0.dist-info/top_level.txt
bower.py-1.0.dist-info/WHEEL
bowerlib/__init__.py
bowerlib/github.py
bowerlib/main.py
