Metadata-Version: 2.0
Name: bower.py
Version: 1.0
Summary: A sample Python project
Home-page: https://github.com/r1chardj0n3s/laughing-robot
Author: Richard Jones
Author-email: r1chardj0n3s@gmail.com
License: Apache 2.0
Keywords: bower javascript
Platform: UNKNOWN
Classifier: Development Status :: 4 - Beta
Classifier: Intended Audience :: Developers
Classifier: Topic :: Software Development :: Build Tools
Classifier: License :: OSI Approved :: Apache Software License
Classifier: Programming Language :: Python :: 3.4
Requires-Dist: requests
Requires-Dist: semantic-version
Requires-Dist: github3.py
